LICENSE
MANIFEST.in
README.md
setup.cfg
setup.py
django_quickbooks/__init__.py
django_quickbooks/admin.py
django_quickbooks/apps.py
django_quickbooks/exceptions.py
django_quickbooks/managers.py
django_quickbooks/models.py
django_quickbooks/queue_manager.py
django_quickbooks/request_builder.py
django_quickbooks/session_manager.py
django_quickbooks/settings.py
django_quickbooks/tasks.py
django_quickbooks/tests.py
django_quickbooks/urls.py
django_quickbooks/utils.py
django_quickbooks/validators.py
django_quickbooks.egg-info/PKG-INFO
django_quickbooks.egg-info/SOURCES.txt
django_quickbooks.egg-info/dependency_links.txt
django_quickbooks.egg-info/requires.txt
django_quickbooks.egg-info/top_level.txt
django_quickbooks/core/__init__.py
django_quickbooks/core/queue_manager.py
django_quickbooks/core/session_manager.py
django_quickbooks/data/customer_add_request.xml
django_quickbooks/data/customer_add_response.xml
django_quickbooks/data/customer_mod_request.xml
django_quickbooks/data/customer_mod_response.xml
django_quickbooks/data/customer_query_request.xml
django_quickbooks/data/customer_query_response.xml
django_quickbooks/data/invoice_add_request.xml
django_quickbooks/data/invoice_add_response.xml
django_quickbooks/data/invoice_mod_request.xml
django_quickbooks/data/invoice_mod_response.xml
django_quickbooks/data/invoice_query_request.xml
django_quickbooks/data/invoice_query_response.xml
django_quickbooks/management/__init__.py
django_quickbooks/migrations/0001_initial.py
django_quickbooks/migrations/0002_auto_20200103_0801.py
django_quickbooks/migrations/0003_qbtask.py
django_quickbooks/migrations/0004_auto_20200122_1140.py
django_quickbooks/migrations/__init__.py
django_quickbooks/objects/__init__.py
django_quickbooks/objects/address.py
django_quickbooks/objects/base.py
django_quickbooks/objects/customer.py
django_quickbooks/objects/invoice.py
django_quickbooks/processors/__init__.py
django_quickbooks/processors/base.py
django_quickbooks/processors/customer.py
django_quickbooks/processors/invoice.py
django_quickbooks/processors/item_service.py
django_quickbooks/services/__init__.py
django_quickbooks/services/base.py
django_quickbooks/services/customer.py
